.DS_Store
gym_jiminy/envs/__init__.py
gym_jiminy/envs/acrobot.py
gym_jiminy/envs/ant.py
gym_jiminy/envs/anymal.py
gym_jiminy/envs/atlas.py
gym_jiminy/envs/cartpole.py
gym_jiminy/envs/cassie.py
gym_jiminy/envs/digit.py
gym_jiminy/envs/py.typed
gym_jiminy/envs/data/bipedal_robots/atlas/atlas.urdf
gym_jiminy/envs/data/bipedal_robots/atlas/atlas_hardware.toml
gym_jiminy/envs/data/bipedal_robots/atlas/atlas_options.toml
gym_jiminy/envs/data/bipedal_robots/atlas/meshes/drc_extremities_diffuse.png
gym_jiminy/envs/data/bipedal_robots/atlas/meshes/drc_torso_head_diffuse.png
gym_jiminy/envs/data/bipedal_robots/atlas/meshes/extremities_diffuse.png
gym_jiminy/envs/data/bipedal_robots/atlas/meshes/extremities_diffuse_unplugged.png
gym_jiminy/envs/data/bipedal_robots/atlas/meshes/head.dae
gym_jiminy/envs/data/bipedal_robots/atlas/meshes/l_foot.dae
gym_jiminy/envs/data/bipedal_robots/atlas/meshes/l_lglut.dae
gym_jiminy/envs/data/bipedal_robots/atlas/meshes/l_lleg.dae
gym_jiminy/envs/data/bipedal_robots/atlas/meshes/l_talus.dae
gym_jiminy/envs/data/bipedal_robots/atlas/meshes/l_uglut.dae
gym_jiminy/envs/data/bipedal_robots/atlas/meshes/l_uleg.dae
gym_jiminy/envs/data/bipedal_robots/atlas/meshes/ltorso.dae
gym_jiminy/envs/data/bipedal_robots/atlas/meshes/mtorso.dae
gym_jiminy/envs/data/bipedal_robots/atlas/meshes/pelvis.dae
gym_jiminy/envs/data/bipedal_robots/atlas/meshes/r_clav.dae
gym_jiminy/envs/data/bipedal_robots/atlas/meshes/r_farm.dae
gym_jiminy/envs/data/bipedal_robots/atlas/meshes/r_foot.dae
gym_jiminy/envs/data/bipedal_robots/atlas/meshes/r_hand.dae
gym_jiminy/envs/data/bipedal_robots/atlas/meshes/r_larm.dae
gym_jiminy/envs/data/bipedal_robots/atlas/meshes/r_lglut.dae
gym_jiminy/envs/data/bipedal_robots/atlas/meshes/r_lleg.dae
gym_jiminy/envs/data/bipedal_robots/atlas/meshes/r_scap.dae
gym_jiminy/envs/data/bipedal_robots/atlas/meshes/r_talus.dae
gym_jiminy/envs/data/bipedal_robots/atlas/meshes/r_uarm.dae
gym_jiminy/envs/data/bipedal_robots/atlas/meshes/r_uglut.dae
gym_jiminy_zoo-1.8.13.dist-info/METADATA
gym_jiminy_zoo-1.8.13.dist-info/WHEEL
gym_jiminy_zoo-1.8.13.dist-info/top_level.txt
gym_jiminy_zoo-1.8.13.dist-info/RECORD
